day2/Combinatinal/Fullsubtract/Fullsubtract.v
module fullsubtract(input a,b,bin,output dif,brw);
xor(dif,a,b,bin);
and(brw,~a,b,bin);
endmodule

day2/fullsubtract/fullsubtract_tb.v
module full_tb();
reg a,b,bin;
wire dif,brw;
fullsubtract uut(a,b,bin,dif,brw);
initial begin
#10 a=0; b=0; bin=0;
#10 a=0; b=0; bin=1;
#10 a=0; b=1; bin=0;
#10 a=0; b=1; bin=1;
#10 a=1; b=0; bin=0;
#10 a=1; b=0; bin=1;
#10 a=1; b=1; bin=0;
#10 a=1; b=1; bin=1;
#10 $finish;
end 
initial begin
$dumpfile("full_tb.vcd");
$dumpvars();
$monitor("%0t | A=%b | B=%b | BIN=%b | DIF=%b | BRW=%b",$time,a,b,bin,dif,brw);
end
endmodule

day2/fullsubtract/full_tb.vcd
$date
	Tue Oct 14 19:42:38 2025
$end
$version
	Icarus Verilog
$end
$timescale
	1s
$end
$scope module full_tb $end
$var wire 1 ! dif $end
$var wire 1 " brw $end
$var reg 1 # a $end
$var reg 1 $ b $end
$var reg 1 % bin $end
$scope module uut $end
$var wire 1 # a $end
$var wire 1 $ b $end
$var wire 1 % bin $end
$var wire 1 " brw $end
$var wire 1 ! dif $end
$upscope $end
$upscope $end
$enddefinitions $end
$comment Show the parameter values. $end
$dumpall
$end
#0
$dumpvars
x%
x$
x#
x"
x!
$end
#10
0"
0!
0%
0$
0#
#20
1!
1%
#30
0%
1$
#40
0!
1"
1%
#50
0"
1!
0%
0$
1#
#60
0!
1%
#70
0%
1$
#80
1!
1%
