day2/Combinatinal/FAusingHA/fausingha.v
module halfadder(input a,b,output sum,cout);
assign sum=a^b;
assign cout=a+b;
endmodule

module fulladder(input a,b,cin,output sum,cout);
wire sumout1,carry1,carry2;
halfadder h1(a,b,sumout1,carry1);
halfadder h2(sumout1,cin,sum,carry2);
or(cout,carry1,carry2);
endmodule

day2/fausingha/fausingha_tb.v
module full_tb();
reg a,b,cin;
wire sum,cout;
fulladder uut(a,b,cin,sum,cout);
initial begin
#10 a=0; b=0; cin=0;
#10 a=0; b=0; cin=1;
#10 a=0; b=1; cin=0;
#10 a=0; b=1; cin=1;
#10 a=1; b=0; cin=0;
#10 a=1; b=0; cin=1;
#10 a=1; b=1; cin=0;
#10 a=1; b=1; cin=1;
#10 $finish;
end
initial begin
$dumpfile("full_tb.vcd");
$dumpvars();
$monitor("%0t|  A=%b | B=%b | cin=%b | SUM=%b | COUT=%b ",$time,a,b,cin,sum,cout);
end
endmodule

day2/fausingha/full_tb.vcd
$date
	Tue Oct 14 12:00:08 2025
$end
$version
	Icarus Verilog
$end
$timescale
	1s
$end
$scope module full_tb $end
$var wire 1 ! sum $end
$var wire 1 " cout $end
$var reg 1 # a $end
$var reg 1 $ b $end
$var reg 1 % cin $end
$scope module uut $end
$var wire 1 # a $end
$var wire 1 $ b $end
$var wire 1 % cin $end
$var wire 1 " cout $end
$var wire 1 & sumout1 $end
$var wire 1 ! sum $end
$var wire 1 ' carry2 $end
$var wire 1 ( carry1 $end
$scope module h1 $end
$var wire 1 # a $end
$var wire 1 $ b $end
$var wire 1 & sum $end
$var wire 1 ( cout $end
$upscope $end
$scope module h2 $end
$var wire 1 & a $end
$var wire 1 % b $end
$var wire 1 ! sum $end
$var wire 1 ' cout $end
$upscope $end
$upscope $end
$upscope $end
$enddefinitions $end
$comment Show the parameter values. $end
$dumpall
$end
#0
$dumpvars
x(
x'
x&
x%
x$
x#
x"
x!
$end
#10
0!
0"
0'
0&
0%
0(
0$
0#
#20
1!
1"
1'
1%
#30
1&
1'
0%
1(
1$
#40
0!
0'
1%
#50
1!
1'
0%
0$
1(
1#
#60
0!
0'
1%
#70
0"
0&
0'
0%
0(
1$
#80
1!
1"
1'
1%
