day2/ripplecarry/rca.v
module rca(input[3:0] a,b,output [3:0]sum,output carry);
wire[2:0]cout;
fulladder f1(a[0],b[0],1'b0,sum[0],cout[0]);
fulladder f2(a[1],b[1],cout[0],sum[1],cout[1]);
fulladder f3(a[2],b[2],cout[1],sum[2],cout[2]);
fulladder f4(a[3],b[3],cout[2],sum[3],carry);
endmodule 


module fulladder(input a,b,cin,output sum,carry);
assign sum = a^b^cin;
assign carry = (a&b)|(b&cin)|(cin&a);
endmodule

day2/Combinatinal/Fulladder/Fulladder_tb.v
module full_tb();
reg a,b,cin;
wire sum,carry;
fulladder uut(.a(a),.b(b),.cin(cin),.sum(sum),.carry(carry));
initial begin
#10 a=0; b=0; cin=0;
#10 a=0; b=0; cin=1;
#10 a=0; b=1; cin=0;
#10 a=0; b=1; cin=1;
#10 a=1; b=0; cin=0;
#10 a=1; b=0; cin=1;
#10 a=1; b=1; cin=0;
#10 a=1; b=1; cin=1;
#10 $finish;
end
initial begin
$dumpfile("full_tb.vcd");
$dumpvars();
$monitor("%0t | A=%b | B=%b | CIN=%b  | SUM=%b | CARRY=%b",$time,a,b,cin,sum,carry);
end 
endmodule

day2/fulladder/full_tb.vcd
$date
	Mon Oct 13 16:20:51 2025
$end
$version
	Icarus Verilog
$end
$timescale
	1s
$end
$scope module full_tb $end
$var wire 1 ! sum $end
$var wire 1 " carry $end
$var reg 1 # a $end
$var reg 1 $ b $end
$var reg 1 % cin $end
$scope module uut $end
$var wire 1 # a $end
$var wire 1 $ b $end
$var wire 1 " carry $end
$var wire 1 % cin $end
$var wire 1 ! sum $end
$upscope $end
$upscope $end
$enddefinitions $end
$comment Show the parameter values. $end
$dumpall
$end
#0
$dumpvars
x%
x$
x#
x"
x!
$end
#10
0"
0!
0%
0$
0#
#20
1!
1%
#30
0%
1$
#40
1"
0!
1%
#50
0"
1!
0%
0$
1#
#60
1"
0!
1%
#70
0%
1$
#80
1!
1%
