day2/fsusinghs/fsusinghs.v
module halfsubtract(input a,b,output dif,brw);
xor(dif,a,b);
and(brw,~a,b);
endmodule 

module fullsubtract(input a,b,bin,output dif,brw);
wire difout1,brw1,brw2;
halfsubtract h1(a,b,difout,brw1);
halfsubtract h2(cin,difout1,dif,brw2);
or(brw,brw1,brw2);
endmodule

day2/fsusinghs/fsusinghs_tb.v
module full_tb();
reg a,b,bin;
wire dif,brw;
fullsubtract uut(a,b,bin,dif,brw);
initial begin 
#10 a=0; b=0; bin=0;
#10 a=0; b=0; bin=1;
#10 a=0; b=1; bin=0;
#10 a=0; b=1; bin=1;
#10 a=1; b=0; bin=0;
#10 a=1; b=0; bin=1;
#10 a=1; b=1; bin=0;
#10 a=1; b=1; bin=1;
#10 $finish;
end
initial begin 
$dumpfile("full_tb.vcd");
$dumpvars();
$monitor("%0t | A=%b | B=%b | BIN=%b | DIF=%b | BRW=%b ",$time,a,b,bin,dif,brw);
end 
endmodule

day2/fsusinghs/full_tb.vcd
$date
	Tue Oct 14 12:22:43 2025
$end
$version
	Icarus Verilog
$end
$timescale
	1s
$end
$scope module full_tb $end
$var wire 1 ! dif $end
$var wire 1 " brw $end
$var reg 1 # a $end
$var reg 1 $ b $end
$var reg 1 % bin $end
$scope module uut $end
$var wire 1 # a $end
$var wire 1 $ b $end
$var wire 1 % bin $end
$var wire 1 " brw $end
$var wire 1 & cin $end
$var wire 1 ' difout1 $end
$var wire 1 ( difout $end
$var wire 1 ! dif $end
$var wire 1 ) brw2 $end
$var wire 1 * brw1 $end
$scope module h1 $end
$var wire 1 # a $end
$var wire 1 $ b $end
$var wire 1 * brw $end
$var wire 1 ( dif $end
$upscope $end
$scope module h2 $end
$var wire 1 & a $end
$var wire 1 ' b $end
$var wire 1 ) brw $end
$var wire 1 ! dif $end
$upscope $end
$upscope $end
$upscope $end
$enddefinitions $end
$comment Show the parameter values. $end
$dumpall
$end
#0
$dumpvars
x*
x)
x(
z'
z&
x%
x$
x#
x"
x!
$end
#10
0*
0(
0%
0$
0#
#20
1%
#30
1"
1(
1*
0%
1$
#40
1%
#50
x"
0*
0%
0$
1#
#60
1%
#70
0(
0%
1$
#80
1%
